{
  "generated": "2026-05-25",
  "categories": {
    "Data & Analytics": {
      "cat_median": 162450,
      "n_jobs": 44,
      "skills": [
        {
          "skill": "data",
          "median": 188000,
          "n": 2,
          "dev": 15.7
        },
        {
          "skill": "cross-functional collaboration",
          "median": 168000,
          "n": 3,
          "dev": 3.4
        },
        {
          "skill": "program management",
          "median": 168000,
          "n": 2,
          "dev": 3.4
        },
        {
          "skill": "cloud networking",
          "median": 168000,
          "n": 2,
          "dev": 3.4
        },
        {
          "skill": "network deployment optimization",
          "median": 168000,
          "n": 2,
          "dev": 3.4
        },
        {
          "skill": "python",
          "median": 135250,
          "n": 2,
          "dev": -16.7
        },
        {
          "skill": "sql",
          "median": 117750,
          "n": 2,
          "dev": -27.5
        },
        {
          "skill": "excel",
          "median": 106250,
          "n": 2,
          "dev": -34.6
        },
        {
          "skill": "tableau",
          "median": 85000,
          "n": 2,
          "dev": -47.7
        }
      ]
    },
    "Other": {
      "cat_median": 148716,
      "n_jobs": 113,
      "skills": [
        {
          "skill": "enterprise",
          "median": 263500,
          "n": 2,
          "dev": 77.2
        },
        {
          "skill": "management",
          "median": 229750,
          "n": 2,
          "dev": 54.5
        },
        {
          "skill": "google cloud",
          "median": 224000,
          "n": 2,
          "dev": 50.6
        },
        {
          "skill": "solutions architect",
          "median": 224000,
          "n": 2,
          "dev": 50.6
        },
        {
          "skill": "sales",
          "median": 214500,
          "n": 2,
          "dev": 44.2
        },
        {
          "skill": "ai tools",
          "median": 213000,
          "n": 2,
          "dev": 43.2
        },
        {
          "skill": "strategic",
          "median": 204030,
          "n": 2,
          "dev": 37.2
        },
        {
          "skill": "pipeline generation",
          "median": 201500,
          "n": 2,
          "dev": 35.5
        },
        {
          "skill": "dlp",
          "median": 201500,
          "n": 2,
          "dev": 35.5
        },
        {
          "skill": "ai security",
          "median": 201500,
          "n": 2,
          "dev": 35.5
        },
        {
          "skill": "sales strategy",
          "median": 201500,
          "n": 2,
          "dev": 35.5
        },
        {
          "skill": "swg",
          "median": 201500,
          "n": 2,
          "dev": 35.5
        },
        {
          "skill": "sase",
          "median": 201500,
          "n": 2,
          "dev": 35.5
        },
        {
          "skill": "regulatory compliance",
          "median": 177250,
          "n": 2,
          "dev": 19.2
        },
        {
          "skill": "cloud",
          "median": 172500,
          "n": 3,
          "dev": 16.0
        },
        {
          "skill": "strategy",
          "median": 165250,
          "n": 2,
          "dev": 11.1
        },
        {
          "skill": "cross-functional collaboration",
          "median": 163500,
          "n": 3,
          "dev": 9.9
        },
        {
          "skill": "data",
          "median": 154000,
          "n": 2,
          "dev": 3.6
        },
        {
          "skill": "specialist",
          "median": 149250,
          "n": 2,
          "dev": 0.4
        },
        {
          "skill": "customer",
          "median": 124750,
          "n": 4,
          "dev": -16.1
        },
        {
          "skill": "billing",
          "median": 124750,
          "n": 2,
          "dev": -16.1
        },
        {
          "skill": "technical",
          "median": 124750,
          "n": 2,
          "dev": -16.1
        },
        {
          "skill": "healthcare",
          "median": 119750,
          "n": 2,
          "dev": -19.5
        },
        {
          "skill": "troubleshooting",
          "median": 111000,
          "n": 3,
          "dev": -25.4
        },
        {
          "skill": "support",
          "median": 111000,
          "n": 3,
          "dev": -25.4
        },
        {
          "skill": "ads",
          "median": 111000,
          "n": 3,
          "dev": -25.4
        },
        {
          "skill": "case management",
          "median": 77000,
          "n": 3,
          "dev": -48.2
        },
        {
          "skill": "clinical supervision",
          "median": 77000,
          "n": 2,
          "dev": -48.2
        },
        {
          "skill": "mental health",
          "median": 77000,
          "n": 3,
          "dev": -48.2
        },
        {
          "skill": "program management",
          "median": 77000,
          "n": 2,
          "dev": -48.2
        }
      ]
    },
    "Management": {
      "cat_median": 192500,
      "n_jobs": 95,
      "skills": [
        {
          "skill": "cross_functional_collaboration",
          "median": 333750,
          "n": 2,
          "dev": 73.4
        },
        {
          "skill": "behavioral health",
          "median": 229600,
          "n": 3,
          "dev": 19.3
        },
        {
          "skill": "mental health",
          "median": 229600,
          "n": 3,
          "dev": 19.3
        },
        {
          "skill": "clinical strategy",
          "median": 229600,
          "n": 3,
          "dev": 19.3
        },
        {
          "skill": "cross-functional collaboration",
          "median": 200000,
          "n": 11,
          "dev": 3.9
        },
        {
          "skill": "infrastructure",
          "median": 184000,
          "n": 8,
          "dev": -4.4
        },
        {
          "skill": "cross-functional",
          "median": 184000,
          "n": 8,
          "dev": -4.4
        },
        {
          "skill": "data center",
          "median": 184000,
          "n": 8,
          "dev": -4.4
        },
        {
          "skill": "stakeholder management",
          "median": 184000,
          "n": 8,
          "dev": -4.4
        },
        {
          "skill": "ml portfolio",
          "median": 184000,
          "n": 8,
          "dev": -4.4
        },
        {
          "skill": "cloud networking",
          "median": 184000,
          "n": 6,
          "dev": -4.4
        },
        {
          "skill": "network deployment optimization",
          "median": 184000,
          "n": 6,
          "dev": -4.4
        },
        {
          "skill": "program management",
          "median": 168000,
          "n": 17,
          "dev": -12.7
        },
        {
          "skill": "clinical",
          "median": 158425,
          "n": 2,
          "dev": -17.7
        },
        {
          "skill": "management",
          "median": 150125,
          "n": 2,
          "dev": -22.0
        },
        {
          "skill": "program",
          "median": 150125,
          "n": 2,
          "dev": -22.0
        }
      ]
    },
    "Product": {
      "cat_median": 186000,
      "n_jobs": 53,
      "skills": [
        {
          "skill": "strategy",
          "median": 260250,
          "n": 2,
          "dev": 39.9
        },
        {
          "skill": "security",
          "median": 240500,
          "n": 3,
          "dev": 29.3
        },
        {
          "skill": "governance",
          "median": 213250,
          "n": 2,
          "dev": 14.7
        },
        {
          "skill": "product",
          "median": 198000,
          "n": 7,
          "dev": 6.5
        },
        {
          "skill": "commercial",
          "median": 198000,
          "n": 3,
          "dev": 6.5
        },
        {
          "skill": "strategic thinking",
          "median": 187750,
          "n": 2,
          "dev": 0.9
        },
        {
          "skill": "cross-functional collaboration",
          "median": 154980,
          "n": 2,
          "dev": -16.7
        },
        {
          "skill": "product support",
          "median": 138500,
          "n": 4,
          "dev": -25.5
        },
        {
          "skill": "solutions",
          "median": 138500,
          "n": 3,
          "dev": -25.5
        },
        {
          "skill": "gup platforms",
          "median": 138500,
          "n": 2,
          "dev": -25.5
        },
        {
          "skill": "google fi",
          "median": 138500,
          "n": 2,
          "dev": -25.5
        },
        {
          "skill": "google store",
          "median": 138500,
          "n": 2,
          "dev": -25.5
        },
        {
          "skill": "client facing",
          "median": 138500,
          "n": 3,
          "dev": -25.5
        },
        {
          "skill": "project management",
          "median": 138500,
          "n": 2,
          "dev": -25.5
        },
        {
          "skill": "consultant",
          "median": 138500,
          "n": 2,
          "dev": -25.5
        },
        {
          "skill": "troubleshooting",
          "median": 138500,
          "n": 2,
          "dev": -25.5
        },
        {
          "skill": "customer",
          "median": 138500,
          "n": 2,
          "dev": -25.5
        },
        {
          "skill": "support",
          "median": 138500,
          "n": 2,
          "dev": -25.5
        }
      ]
    },
    "Engineering": {
      "cat_median": 187500,
      "n_jobs": 142,
      "skills": [
        {
          "skill": "distributed_systems",
          "median": 299528,
          "n": 2,
          "dev": 59.7
        },
        {
          "skill": "technical leadership",
          "median": 296500,
          "n": 2,
          "dev": 58.1
        },
        {
          "skill": "typescript",
          "median": 296500,
          "n": 2,
          "dev": 58.1
        },
        {
          "skill": "nodejs",
          "median": 296500,
          "n": 2,
          "dev": 58.1
        },
        {
          "skill": "security",
          "median": 280750,
          "n": 2,
          "dev": 49.7
        },
        {
          "skill": "java",
          "median": 266278,
          "n": 2,
          "dev": 42.0
        },
        {
          "skill": "cross-functional collaboration",
          "median": 265500,
          "n": 3,
          "dev": 41.6
        },
        {
          "skill": "react",
          "median": 243500,
          "n": 3,
          "dev": 29.9
        },
        {
          "skill": "software_engineering",
          "median": 235028,
          "n": 2,
          "dev": 25.3
        },
        {
          "skill": "applied ai",
          "median": 224000,
          "n": 3,
          "dev": 19.5
        },
        {
          "skill": "conversational agents",
          "median": 224000,
          "n": 2,
          "dev": 19.5
        },
        {
          "skill": "generative ai",
          "median": 224000,
          "n": 3,
          "dev": 19.5
        },
        {
          "skill": "full-stack applications",
          "median": 224000,
          "n": 2,
          "dev": 19.5
        },
        {
          "skill": "cloud platforms",
          "median": 224000,
          "n": 2,
          "dev": 19.5
        },
        {
          "skill": "google cloud",
          "median": 213000,
          "n": 5,
          "dev": 13.6
        },
        {
          "skill": "architecture",
          "median": 205000,
          "n": 2,
          "dev": 9.3
        },
        {
          "skill": "data center",
          "median": 204750,
          "n": 2,
          "dev": 9.2
        },
        {
          "skill": "cloud architecture",
          "median": 200250,
          "n": 2,
          "dev": 6.8
        },
        {
          "skill": "problem solving",
          "median": 198875,
          "n": 2,
          "dev": 6.1
        },
        {
          "skill": "infrastructure",
          "median": 193750,
          "n": 2,
          "dev": 3.3
        },
        {
          "skill": "python",
          "median": 187500,
          "n": 13,
          "dev": 0.0
        },
        {
          "skill": "customer engineering",
          "median": 180000,
          "n": 2,
          "dev": -4.0
        },
        {
          "skill": "cloud",
          "median": 171250,
          "n": 8,
          "dev": -8.7
        },
        {
          "skill": "product",
          "median": 171250,
          "n": 2,
          "dev": -8.7
        },
        {
          "skill": "customer",
          "median": 171250,
          "n": 2,
          "dev": -8.7
        },
        {
          "skill": "solutions",
          "median": 171250,
          "n": 2,
          "dev": -8.7
        },
        {
          "skill": "technical",
          "median": 171250,
          "n": 2,
          "dev": -8.7
        },
        {
          "skill": "expertise",
          "median": 171250,
          "n": 2,
          "dev": -8.7
        },
        {
          "skill": "support",
          "median": 171250,
          "n": 2,
          "dev": -8.7
        },
        {
          "skill": "enterprise_it_infrastructure",
          "median": 155000,
          "n": 5,
          "dev": -17.3
        }
      ]
    },
    "Sales": {
      "cat_median": 142250,
      "n_jobs": 12,
      "skills": []
    },
    "Operations": {
      "cat_median": 158150,
      "n_jobs": 22,
      "skills": [
        {
          "skill": "operations",
          "median": 188225,
          "n": 2,
          "dev": 19.0
        },
        {
          "skill": "cross_functional_collaboration",
          "median": 148625,
          "n": 2,
          "dev": -6.0
        }
      ]
    },
    "Design": {
      "cat_median": 176500,
      "n_jobs": 6,
      "skills": []
    },
    "Finance": {
      "cat_median": 144912,
      "n_jobs": 4,
      "skills": []
    }
  }
}